{
    "version":1,
    "group":1,
    "articles":[
        {
            "language":0,
            "title":"欢迎",
            "author":"迎风听雨",
            "paragraphs":[
                {
                    "type":"text",
                    "text":"欢迎使用PopStudio！这里是教程区，你可以在这里查询本工具的使用教程！",
                    "fontsize":"Middle"
                },
                {
                    "type":"image",
                    "src":""
                },
                {
                    "type":"link",
                    "text":"解包打包",
                    "fontsize":"Middle",
                    "url":"Article(Package@1)"
                }
            ]
        }
    ]
    
}